can_01_chatbot/__init__.py
can_01_chatbot/can01.py
tests/__init__.py
tests/test_can01.py
tests/test_imports.py
can_01_chatbot-0.4.dist-info/LICENSE
can_01_chatbot-0.4.dist-info/METADATA
can_01_chatbot-0.4.dist-info/WHEEL
can_01_chatbot-0.4.dist-info/top_level.txt
can_01_chatbot-0.4.dist-info/RECORD
